latechclfl2020/__init__.py
latechclfl2020/constants.py
latechclfl2020/utils.py
latechclfl2020/dlh/LEMMATISED_DLH_PROPER_NOUNS.txt
latechclfl2020/dlh/LEMMATIZED_DLH_CLEAN_PERSON_NAMES.txt
latechclfl2020/dlh/LEMMATIZED_DLH_CLEAN_PLACES.txt
latechclfl2020/dlh/LEMMATIZED_DLH_CLEAN_PROPER_NOUNS.txt
latechclfl2020/dlh/__init__.py
latechclfl2020/dlh/data.py
latechclfl2020/dlh/scripts.py
latechclfl2020/dlh/gregoire_de_tours_html/1.html
latechclfl2020/dlh/gregoire_de_tours_html/10.html
latechclfl2020/dlh/gregoire_de_tours_html/11.html
latechclfl2020/dlh/gregoire_de_tours_html/2.html
latechclfl2020/dlh/gregoire_de_tours_html/3.html
latechclfl2020/dlh/gregoire_de_tours_html/4.html
latechclfl2020/dlh/gregoire_de_tours_html/5.html
latechclfl2020/dlh/gregoire_de_tours_html/6.html
latechclfl2020/dlh/gregoire_de_tours_html/7.html
latechclfl2020/dlh/gregoire_de_tours_html/8.html
latechclfl2020/dlh/gregoire_de_tours_html/9.html
latechclfl2020/dlh/gregoire_de_tours_txt/1.txt
latechclfl2020/dlh/gregoire_de_tours_txt/10.txt
latechclfl2020/dlh/gregoire_de_tours_txt/2.txt
latechclfl2020/dlh/gregoire_de_tours_txt/3.txt
latechclfl2020/dlh/gregoire_de_tours_txt/4.txt
latechclfl2020/dlh/gregoire_de_tours_txt/5.txt
latechclfl2020/dlh/gregoire_de_tours_txt/6.txt
latechclfl2020/dlh/gregoire_de_tours_txt/7.txt
latechclfl2020/dlh/gregoire_de_tours_txt/8.txt
latechclfl2020/dlh/gregoire_de_tours_txt/9.txt
latechclfl2020/dlh/gregoire_de_tours_txt/preface.txt
latechclfl2020/dlh/gregory_of_tours_html/1.html
latechclfl2020/dlh/gregory_of_tours_html/10.html
latechclfl2020/dlh/gregory_of_tours_html/2.html
latechclfl2020/dlh/gregory_of_tours_html/3.html
latechclfl2020/dlh/gregory_of_tours_html/4.html
latechclfl2020/dlh/gregory_of_tours_html/5.html
latechclfl2020/dlh/gregory_of_tours_html/6.html
latechclfl2020/dlh/gregory_of_tours_html/7.html
latechclfl2020/dlh/gregory_of_tours_html/8.html
latechclfl2020/dlh/gregory_of_tours_html/9.html
latechclfl2020/dlh/gregory_of_tours_txt/1.txt
latechclfl2020besnier-1.1.0.dist-info/METADATA
latechclfl2020besnier-1.1.0.dist-info/WHEEL
latechclfl2020besnier-1.1.0.dist-info/top_level.txt
latechclfl2020besnier-1.1.0.dist-info/zip-safe
latechclfl2020besnier-1.1.0.dist-info/RECORD
