Metadata-Version: 2.1
Name: latechclfl2020besnier
Version: 1.1.0
Summary: UNKNOWN
Home-page: https://www.clementbesnier.fr/dlh-vol-nib
Author: Clément Besnier
Author-email: clem@clementbesnier.fr
License: Creative Commons Attribution 4.0 International Licence
Keywords: old-norse,middle-high-german,latin,network analysis
Platform: UNKNOWN
Classifier: Programming Language :: Python :: 3
Requires-Python: >=3.6
Requires-Dist: beautifulsoup4 (>=4.9.1)
Requires-Dist: cltk (>=0.1.111)
Requires-Dist: greek-accentuation (>=1.2.0)
Requires-Dist: jupyter
Requires-Dist: lxml
Requires-Dist: matplotlib
Requires-Dist: networkx (==2.4)
Requires-Dist: norsecorpus (>=1.0.2)
Requires-Dist: notebook (>=6.1.5)
Requires-Dist: numpy (>=1.19.1)
Requires-Dist: requests (>=2.24.0)
Requires-Dist: scikit-learn (>=0.23.1)
Requires-Dist: scipy (>=1.4.1)
Requires-Dist: sigurd (>=1.2.9)
